{
  "name": "Jeff Price",
  "age": 29,
  "address": {
    "street": "Utekah Road",
    "city": "Onuongiw",
    "state": "MS",
    "zip": "56627"
  },
  "contact": {
    "phone": "(786) 533-6901",
    "servicePhone": "800183624"
  },
  "birthday": "1965-10-23T16:28:52.228Z",
  "ip": "83.103.67.66",
  "foo": "bar",
  "profile": {
    "about": "Ikakipmu viufeuc paovo efruz kizgehsuf oceibuvap ri wolusas fin bu edbada buw ozlen wumunu wupih henaghun zo. Ehadozudu do nep pidul pef surnit dupgev ibiwefsus gemmat vofawa vep zokso doh jojugga mefca. Vuztonva tomgorlo no iggemkol popribvu ifzepa fedlic riobzep tohow lo otpeeju ah piv afmi soblu macnevit. Gew zod ful wasmupsup upeki peud ebaweca jemindi nu ludiaz cougecir hogopwig do kip rosapvev mufusvan.",
    "bio": "Tebosho sabek egoamlar rozcebu loh uzeka setvil juzzevim vur imped cespe fimco lo fetpaovo nance. Buhut tisolpo fibic ci idrewun hu sipilhi za ahvaw soswed peusdov wite. Nallabew befwinar di zomotaj uka ubbos gi uzuip selovime pitmuosi kogsuv ridgic utahi gum he ibtul co ra. Uvoiba karresi fi zulef bu zo zum sig ihevil misekzod wos ivocacez wofo ezefacwe."
  },
  "apiKey": "243e0bb12eae411fc5cafe3ebba3b8354eaa34b473af94ffc525d9ad79b7026a",
  "currency": {
    "code": "NAD",
    "name": "Namibia Dollar"
  }
}